yoyo_cloud/__init__.py
yoyo_cloud/migrations.py
yoyo_cloud/s3_migrations.py
yoyo_cloud/tests/conftest.py
yoyo_cloud/tests/test_s3_migrations.py
yoyo_cloud-0.1.0.dist-info/METADATA
yoyo_cloud-0.1.0.dist-info/WHEEL
yoyo_cloud-0.1.0.dist-info/RECORD
