Metadata-Version: 2.1
Name: yoyo-cloud
Version: 0.1.0
Summary: Run SQL migrations stored in the cloud.
Author: Fasih Khatib
Author-email: hellofasih.confound928@passinbox.com
Requires-Python: >=3.12,<4.0
Classifier: Programming Language :: Python :: 3
Classifier: Programming Language :: Python :: 3.12
Requires-Dist: s3fs (>=2024.3.1,<2025.0.0)
Requires-Dist: setuptools (>=69.2.0,<70.0.0)
Requires-Dist: yoyo-migrations (>=8.2.0,<9.0.0)
